nnpipeline/__init__.py
nnpipeline/fabricated/ExponentialAutoEncoder.py
nnpipeline/prototype/BasePipe.py
nnpipeline/prototype/Pipe.py
nnpipeline/prototype/composition/LinearExponentialComposition.py
nnpipeline/prototype/joint/LinearJoint.py
nnpipeline/prototype/linear/LinearCylinder.py
nnpipeline/prototype/linear/LinearExponentialDecoder.py
nnpipeline/prototype/linear/LinearExponentialEncoder.py
nnpipeline/tools/__init__.py
fish_nnpipeline-0.0.2.dist-info/LICENSE
fish_nnpipeline-0.0.2.dist-info/METADATA
fish_nnpipeline-0.0.2.dist-info/WHEEL
fish_nnpipeline-0.0.2.dist-info/top_level.txt
fish_nnpipeline-0.0.2.dist-info/RECORD
