Metadata-Version: 2.2
Name: fish-nnpipeline
Version: 0.0.2
Summary: Neural Network Pipeline that helps you to build intricate network more easy way.
Author-email: 안형준 <gatesplan@gmail.com>
License: Copyright <YEAR> <COPYRIGHT HOLDER>
Project-URL: Homepage, https://github.com/gatesplan/nnpipeline
Project-URL: Issues, https://github.com/gatesplan/nnpipeline/issues
Keywords: torch,machine-learning,builder
Classifier: Programming Language :: Python :: 3
Classifier: Programming Language :: Python :: 3.10
Classifier: Programming Language :: Python :: 3.11
Classifier: Programming Language :: Python :: 3.12
Classifier: Programming Language :: Python :: 3.13
Classifier: Operating System :: OS Independent
Classifier: License :: OSI Approved :: MIT License
Requires-Python: <4.0,>=3.10
License-File: LICENSE
Requires-Dist: torch>=2.1
